{"sid": "1710", "candles": [{"date": "2025-10-17", "open": 12.2, "high": 12.55, "low": 12.15, "close": 12.4, "volume": 1406838}, {"date": "2025-10-20", "open": 12.45, "high": 12.5, "low": 12.0, "close": 12.05, "volume": 1749998}, {"date": "2025-10-21", "open": 12.1, "high": 12.2, "low": 12.05, "close": 12.15, "volume": 694983}, {"date": "2025-10-22", "open": 12.1, "high": 12.35, "low": 12.1, "close": 12.15, "volume": 677902}, {"date": "2025-10-23", "open": 12.15, "high": 12.4, "low": 12.05, "close": 12.35, "volume": 1271833}, {"date": "2025-10-27", "open": 12.35, "high": 12.5, "low": 12.3, "close": 12.4, "volume": 773244}, {"date": "2025-10-28", "open": 12.4, "high": 12.4, "low": 12.2, "close": 12.2, "volume": 614382}, {"date": "2025-10-29", "open": 12.2, "high": 12.3, "low": 12.1, "close": 12.2, "volume": 484190}, {"date": "2025-10-30", "open": 12.15, "high": 12.2, "low": 11.8, "close": 11.95, "volume": 1824932}, {"date": "2025-10-31", "open": 12.0, "high": 12.0, "low": 11.75, "close": 11.95, "volume": 1600237}, {"date": "2025-11-03", "open": 11.95, "high": 11.95, "low": 11.6, "close": 11.7, "volume": 1485665}, {"date": "2025-11-04", "open": 11.6, "high": 11.8, "low": 11.55, "close": 11.8, "volume": 852894}, {"date": "2025-11-05", "open": 11.65, "high": 11.75, "low": 11.45, "close": 11.75, "volume": 1014893}, {"date": "2025-11-06", "open": 11.75, "high": 12.25, "low": 11.7, "close": 12.15, "volume": 1464863}, {"date": "2025-11-07", "open": 12.05, "high": 12.3, "low": 12.0, "close": 12.1, "volume": 1151134}, {"date": "2025-11-10", "open": 12.05, "high": 12.05, "low": 11.8, "close": 11.95, "volume": 649879}, {"date": "2025-11-11", "open": 11.9, "high": 12.2, "low": 11.9, "close": 12.15, "volume": 503550}, {"date": "2025-11-12", "open": 12.15, "high": 12.6, "low": 12.15, "close": 12.4, "volume": 3002720}, {"date": "2025-11-13", "open": 12.45, "high": 12.95, "low": 12.45, "close": 12.75, "volume": 3458810}, {"date": "2025-11-14", "open": 12.65, "high": 12.9, "low": 12.55, "close": 12.55, "volume": 1551262}, {"date": "2025-11-17", "open": 12.5, "high": 12.65, "low": 12.2, "close": 12.3, "volume": 1062634}, {"date": "2025-11-18", "open": 12.2, "high": 12.2, "low": 11.85, "close": 11.9, "volume": 1294590}, {"date": "2025-11-19", "open": 11.95, "high": 11.95, "low": 11.7, "close": 11.75, "volume": 987569}, {"date": "2025-11-20", "open": 11.9, "high": 12.0, "low": 11.8, "close": 11.95, "volume": 478434}, {"date": "2025-11-21", "open": 11.9, "high": 11.95, "low": 11.75, "close": 11.75, "volume": 941322}, {"date": "2025-11-24", "open": 11.8, "high": 11.9, "low": 11.6, "close": 11.7, "volume": 910236}, {"date": "2025-11-25", "open": 11.75, "high": 11.85, "low": 11.6, "close": 11.7, "volume": 691177}, {"date": "2025-11-26", "open": 11.75, "high": 11.95, "low": 11.75, "close": 11.9, "volume": 492631}, {"date": "2025-11-27", "open": 11.8, "high": 12.05, "low": 11.8, "close": 12.05, "volume": 605510}, {"date": "2025-11-28", "open": 12.05, "high": 12.25, "low": 12.05, "close": 12.15, "volume": 730200}, {"date": "2025-12-01", "open": 12.2, "high": 12.55, "low": 12.2, "close": 12.45, "volume": 1964405}, {"date": "2025-12-02", "open": 12.55, "high": 13.15, "low": 12.45, "close": 12.9, "volume": 5805565}, {"date": "2025-12-03", "open": 13.0, "high": 13.05, "low": 12.6, "close": 12.8, "volume": 2405605}, {"date": "2025-12-04", "open": 12.8, "high": 12.8, "low": 12.55, "close": 12.65, "volume": 917371}, {"date": "2025-12-05", "open": 12.6, "high": 12.65, "low": 12.35, "close": 12.4, "volume": 962199}, {"date": "2025-12-08", "open": 12.45, "high": 12.5, "low": 12.2, "close": 12.3, "volume": 764875}, {"date": "2025-12-09", "open": 12.3, "high": 12.35, "low": 12.1, "close": 12.3, "volume": 657245}, {"date": "2025-12-10", "open": 12.4, "high": 12.4, "low": 12.15, "close": 12.15, "volume": 874429}, {"date": "2025-12-11", "open": 12.2, "high": 12.3, "low": 12.2, "close": 12.2, "volume": 751100}, {"date": "2025-12-12", "open": 12.4, "high": 12.7, "low": 12.3, "close": 12.35, "volume": 1185585}, {"date": "2025-12-15", "open": 12.25, "high": 12.55, "low": 12.25, "close": 12.35, "volume": 620106}, {"date": "2025-12-16", "open": 12.3, "high": 12.3, "low": 12.0, "close": 12.05, "volume": 1078614}, {"date": "2025-12-17", "open": 12.1, "high": 12.2, "low": 11.9, "close": 11.95, "volume": 1475524}, {"date": "2025-12-18", "open": 11.95, "high": 12.05, "low": 11.9, "close": 11.95, "volume": 624394}, {"date": "2025-12-19", "open": 12.0, "high": 12.15, "low": 12.0, "close": 12.05, "volume": 437368}, {"date": "2025-12-22", "open": 12.1, "high": 12.2, "low": 12.05, "close": 12.1, "volume": 580353}, {"date": "2025-12-23", "open": 12.15, "high": 12.3, "low": 12.1, "close": 12.2, "volume": 787802}, {"date": "2025-12-24", "open": 12.2, "high": 12.3, "low": 11.95, "close": 12.0, "volume": 1524738}, {"date": "2025-12-26", "open": 12.1, "high": 12.2, "low": 12.0, "close": 12.1, "volume": 432370}, {"date": "2025-12-29", "open": 12.15, "high": 12.3, "low": 12.15, "close": 12.15, "volume": 1183236}, {"date": "2025-12-30", "open": 12.1, "high": 12.35, "low": 12.0, "close": 12.3, "volume": 1204977}, {"date": "2025-12-31", "open": 12.35, "high": 12.55, "low": 12.25, "close": 12.45, "volume": 2316790}, {"date": "2026-01-02", "open": 12.45, "high": 12.45, "low": 12.1, "close": 12.25, "volume": 1548360}, {"date": "2026-01-05", "open": 12.2, "high": 12.2, "low": 12.0, "close": 12.05, "volume": 1494430}, {"date": "2026-01-06", "open": 12.05, "high": 12.25, "low": 11.95, "close": 12.15, "volume": 1329537}, {"date": "2026-01-07", "open": 12.2, "high": 13.05, "low": 12.2, "close": 12.9, "volume": 6715180}, {"date": "2026-01-08", "open": 12.9, "high": 13.25, "low": 12.7, "close": 12.7, "volume": 2971079}, {"date": "2026-01-09", "open": 12.8, "high": 12.9, "low": 12.45, "close": 12.55, "volume": 1588630}, {"date": "2026-01-12", "open": 12.55, "high": 12.75, "low": 12.4, "close": 12.65, "volume": 1339608}, {"date": "2026-01-13", "open": 12.75, "high": 12.75, "low": 12.4, "close": 12.7, "volume": 1081600}, {"date": "2026-01-14", "open": 12.8, "high": 13.0, "low": 12.8, "close": 12.9, "volume": 2318311}, {"date": "2026-01-15", "open": 12.8, "high": 13.2, "low": 12.75, "close": 13.05, "volume": 3192256}, {"date": "2026-01-16", "open": 13.1, "high": 13.15, "low": 12.7, "close": 12.75, "volume": 2099322}, {"date": "2026-01-19", "open": 12.7, "high": 13.1, "low": 12.65, "close": 13.0, "volume": 1726213}, {"date": "2026-01-20", "open": 12.9, "high": 13.05, "low": 12.65, "close": 12.7, "volume": 1263788}, {"date": "2026-01-21", "open": 12.7, "high": 12.7, "low": 12.4, "close": 12.5, "volume": 1752331}, {"date": "2026-01-22", "open": 12.6, "high": 12.65, "low": 12.3, "close": 12.35, "volume": 1142699}, {"date": "2026-01-23", "open": 12.5, "high": 12.75, "low": 12.4, "close": 12.5, "volume": 1153270}, {"date": "2026-01-26", "open": 12.9, "high": 13.75, "low": 12.9, "close": 13.75, "volume": 7875234}, {"date": "2026-01-27", "open": 14.0, "high": 14.65, "low": 13.15, "close": 13.85, "volume": 22451582}, {"date": "2026-01-28", "open": 14.05, "high": 14.2, "low": 13.5, "close": 13.95, "volume": 7170905}, {"date": "2026-01-29", "open": 13.95, "high": 14.0, "low": 13.45, "close": 13.55, "volume": 4404491}, {"date": "2026-01-30", "open": 13.55, "high": 13.55, "low": 13.25, "close": 13.3, "volume": 2346262}, {"date": "2026-02-02", "open": 13.2, "high": 13.25, "low": 12.7, "close": 12.75, "volume": 2790160}, {"date": "2026-02-03", "open": 12.9, "high": 12.9, "low": 12.55, "close": 12.7, "volume": 2116112}, {"date": "2026-02-04", "open": 12.6, "high": 13.25, "low": 12.6, "close": 13.05, "volume": 2410259}, {"date": "2026-02-05", "open": 13.0, "high": 13.15, "low": 12.85, "close": 12.9, "volume": 1024964}, {"date": "2026-02-06", "open": 12.8, "high": 12.85, "low": 12.45, "close": 12.55, "volume": 1604603}, {"date": "2026-02-09", "open": 12.7, "high": 12.8, "low": 12.55, "close": 12.7, "volume": 1557030}, {"date": "2026-02-10", "open": 12.7, "high": 12.7, "low": 12.35, "close": 12.55, "volume": 2672875}, {"date": "2026-02-11", "open": 12.6, "high": 12.65, "low": 12.45, "close": 12.6, "volume": 1097375}, {"date": "2026-02-23", "open": 12.7, "high": 13.35, "low": 12.65, "close": 13.2, "volume": 3994163}, {"date": "2026-02-24", "open": 13.3, "high": 13.75, "low": 13.3, "close": 13.55, "volume": 4192947}, {"date": "2026-02-25", "open": 13.8, "high": 13.9, "low": 13.3, "close": 13.55, "volume": 2809415}, {"date": "2026-03-02", "open": 13.15, "high": 13.5, "low": 12.75, "close": 12.75, "volume": 2581645}, {"date": "2026-03-03", "open": 12.8, "high": 13.3, "low": 12.6, "close": 13.15, "volume": 2938569}, {"date": "2026-03-04", "open": 13.2, "high": 13.2, "low": 12.4, "close": 12.5, "volume": 3230408}, {"date": "2026-03-05", "open": 12.65, "high": 12.85, "low": 12.45, "close": 12.8, "volume": 1403853}, {"date": "2026-03-06", "open": 12.65, "high": 13.85, "low": 12.65, "close": 13.7, "volume": 8576604}, {"date": "2026-03-09", "open": 14.3, "high": 14.8, "low": 13.25, "close": 13.45, "volume": 13002536}, {"date": "2026-03-10", "open": 13.3, "high": 13.9, "low": 13.3, "close": 13.8, "volume": 5692733}, {"date": "2026-03-11", "open": 13.55, "high": 13.7, "low": 13.2, "close": 13.5, "volume": 3822963}, {"date": "2026-03-12", "open": 13.6, "high": 14.4, "low": 13.45, "close": 14.0, "volume": 11036899}, {"date": "2026-03-13", "open": 14.2, "high": 14.4, "low": 13.7, "close": 14.1, "volume": 6568941}, {"date": "2026-03-16", "open": 14.2, "high": 14.45, "low": 13.6, "close": 13.6, "volume": 4443369}, {"date": "2026-03-17", "open": 13.6, "high": 13.7, "low": 13.35, "close": 13.4, "volume": 2798540}, {"date": "2026-03-18", "open": 13.55, "high": 13.7, "low": 13.4, "close": 13.5, "volume": 2425311}, {"date": "2026-03-19", "open": 14.1, "high": 14.35, "low": 13.75, "close": 13.85, "volume": 2281466}, {"date": "2026-03-20", "open": 15.85, "high": 16.3, "low": 15.25, "close": 15.35, "volume": 49853061}, {"date": "2026-03-23", "open": 15.45, "high": 16.85, "low": 15.35, "close": 15.7, "volume": 34734430}, {"date": "2026-03-24", "open": 15.25, "high": 15.3, "low": 14.2, "close": 15.0, "volume": 18342247}, {"date": "2026-03-25", "open": 14.7, "high": 14.7, "low": 13.95, "close": 14.3, "volume": 12809020}, {"date": "2026-03-26", "open": 14.65, "high": 15.05, "low": 14.4, "close": 14.5, "volume": 12056140}, {"date": "2026-03-27", "open": 15.3, "high": 15.65, "low": 14.75, "close": 14.95, "volume": 20834992}, {"date": "2026-03-30", "open": 15.5, "high": 16.0, "low": 15.2, "close": 15.55, "volume": 27507519}, {"date": "2026-03-31", "open": 15.5, "high": 15.6, "low": 14.4, "close": 14.5, "volume": 19931644}, {"date": "2026-04-01", "open": 14.3, "high": 14.9, "low": 14.2, "close": 14.55, "volume": 12997153}, {"date": "2026-04-02", "open": 14.7, "high": 14.7, "low": 14.2, "close": 14.2, "volume": 4001539}, {"date": "2026-04-07", "open": 14.25, "high": 14.45, "low": 14.0, "close": 14.15, "volume": 7026926}, {"date": "2026-04-08", "open": 14.35, "high": 14.35, "low": 13.65, "close": 13.65, "volume": 1931391}, {"date": "2026-04-09", "open": 13.7, "high": 14.0, "low": 13.6, "close": 13.8, "volume": 7735624}, {"date": "2026-04-10", "open": 13.6, "high": 13.85, "low": 13.4, "close": 13.55, "volume": 7829752}, {"date": "2026-04-13", "open": 13.7, "high": 14.2, "low": 13.7, "close": 14.0, "volume": 1642000}, {"date": "2026-04-14", "open": 14.4, "high": 14.75, "low": 14.25, "close": 14.55, "volume": 4885727}, {"date": "2026-04-15", "open": 14.45, "high": 14.5, "low": 13.7, "close": 13.7, "volume": 6612120}, {"date": "2026-04-16", "open": 13.85, "high": 13.9, "low": 13.7, "close": 13.9, "volume": 1074108}, {"date": "2026-04-17", "open": 13.95, "high": 14.15, "low": 13.95, "close": 14.1, "volume": 319000}, {"date": "2026-04-20", "open": 13.7, "high": 13.85, "low": 13.45, "close": 13.5, "volume": 4131186}, {"date": "2026-04-21", "open": 13.55, "high": 13.8, "low": 13.2, "close": 13.55, "volume": 6290472}, {"date": "2026-04-22", "open": 13.55, "high": 14.05, "low": 13.45, "close": 13.6, "volume": 6713871}]}