{"sid": "6703", "candles": [{"date": "2025-09-17", "open": 117.5, "high": 120.5, "low": 117.5, "close": 119.0, "volume": 51002}, {"date": "2025-09-18", "open": 119.0, "high": 119.0, "low": 118.0, "close": 119.0, "volume": 17212}, {"date": "2025-09-19", "open": 119.0, "high": 119.0, "low": 117.5, "close": 117.5, "volume": 44270}, {"date": "2025-09-22", "open": 117.5, "high": 118.5, "low": 117.0, "close": 117.5, "volume": 48057}, {"date": "2025-09-23", "open": 117.5, "high": 118.0, "low": 117.0, "close": 118.0, "volume": 20314}, {"date": "2025-09-24", "open": 118.0, "high": 118.5, "low": 117.0, "close": 117.0, "volume": 36000}, {"date": "2025-09-25", "open": 118.0, "high": 119.0, "low": 117.0, "close": 118.0, "volume": 38030}, {"date": "2025-09-26", "open": 117.5, "high": 117.5, "low": 115.5, "close": 115.5, "volume": 46585}, {"date": "2025-09-30", "open": 115.0, "high": 117.5, "low": 115.0, "close": 117.5, "volume": 66529}, {"date": "2025-10-01", "open": 118.0, "high": 118.0, "low": 116.5, "close": 117.0, "volume": 22254}, {"date": "2025-10-02", "open": 117.5, "high": 118.0, "low": 116.5, "close": 118.0, "volume": 19438}, {"date": "2025-10-03", "open": 118.0, "high": 118.0, "low": 116.0, "close": 116.0, "volume": 24400}, {"date": "2025-10-07", "open": 115.5, "high": 115.5, "low": 112.0, "close": 113.0, "volume": 128157}, {"date": "2025-10-08", "open": 112.5, "high": 114.5, "low": 112.5, "close": 113.0, "volume": 24020}, {"date": "2025-10-09", "open": 113.5, "high": 114.0, "low": 112.5, "close": 113.5, "volume": 57400}, {"date": "2025-10-13", "open": 110.0, "high": 112.0, "low": 108.5, "close": 111.0, "volume": 112653}, {"date": "2025-10-14", "open": 111.5, "high": 112.5, "low": 109.5, "close": 112.0, "volume": 41011}, {"date": "2025-10-15", "open": 111.0, "high": 111.0, "low": 108.5, "close": 109.0, "volume": 83700}, {"date": "2025-10-16", "open": 111.5, "high": 111.5, "low": 109.0, "close": 109.0, "volume": 15154}, {"date": "2025-10-17", "open": 109.0, "high": 109.0, "low": 107.5, "close": 108.0, "volume": 68772}, {"date": "2025-10-20", "open": 108.5, "high": 108.5, "low": 108.0, "close": 108.5, "volume": 19270}, {"date": "2025-10-21", "open": 109.5, "high": 110.0, "low": 108.0, "close": 108.5, "volume": 20090}, {"date": "2025-10-22", "open": 108.5, "high": 109.5, "low": 106.0, "close": 109.0, "volume": 234104}, {"date": "2025-10-23", "open": 108.5, "high": 109.0, "low": 107.5, "close": 107.5, "volume": 31123}, {"date": "2025-10-27", "open": 108.0, "high": 108.0, "low": 106.5, "close": 107.0, "volume": 31231}, {"date": "2025-10-28", "open": 107.0, "high": 107.5, "low": 106.5, "close": 107.0, "volume": 20025}, {"date": "2025-10-29", "open": 106.5, "high": 107.0, "low": 105.0, "close": 105.5, "volume": 59666}, {"date": "2025-10-30", "open": 106.0, "high": 106.0, "low": 104.0, "close": 104.5, "volume": 57101}, {"date": "2025-10-31", "open": 105.0, "high": 105.0, "low": 104.0, "close": 104.0, "volume": 16100}, {"date": "2025-11-03", "open": 103.5, "high": 104.0, "low": 102.0, "close": 102.0, "volume": 83666}, {"date": "2025-11-04", "open": 101.5, "high": 102.0, "low": 100.5, "close": 100.5, "volume": 95923}, {"date": "2025-11-05", "open": 100.5, "high": 102.5, "low": 99.5, "close": 102.0, "volume": 156333}, {"date": "2025-11-06", "open": 103.0, "high": 106.5, "low": 103.0, "close": 105.5, "volume": 33003}, {"date": "2025-11-07", "open": 105.0, "high": 105.0, "low": 103.0, "close": 103.0, "volume": 28005}, {"date": "2025-11-10", "open": 112.5, "high": 113.0, "low": 108.5, "close": 110.5, "volume": 310017}, {"date": "2025-11-11", "open": 110.5, "high": 110.5, "low": 107.5, "close": 108.5, "volume": 56068}, {"date": "2025-11-12", "open": 108.0, "high": 108.5, "low": 107.5, "close": 108.0, "volume": 18762}, {"date": "2025-11-13", "open": 109.0, "high": 109.5, "low": 107.5, "close": 109.5, "volume": 51001}, {"date": "2025-11-14", "open": 109.0, "high": 109.0, "low": 107.5, "close": 107.5, "volume": 20135}, {"date": "2025-11-17", "open": 108.0, "high": 108.0, "low": 105.5, "close": 106.0, "volume": 33037}, {"date": "2025-11-18", "open": 106.5, "high": 106.5, "low": 103.0, "close": 104.0, "volume": 42534}, {"date": "2025-11-19", "open": 103.5, "high": 104.0, "low": 103.0, "close": 103.5, "volume": 25011}, {"date": "2025-11-20", "open": 105.5, "high": 105.5, "low": 103.5, "close": 104.5, "volume": 16025}, {"date": "2025-11-21", "open": 102.5, "high": 104.5, "low": 102.5, "close": 102.5, "volume": 39020}, {"date": "2025-11-24", "open": 103.0, "high": 103.5, "low": 102.5, "close": 103.0, "volume": 27060}, {"date": "2025-11-25", "open": 99.8, "high": 103.5, "low": 99.8, "close": 103.5, "volume": 128794}, {"date": "2025-11-26", "open": 103.5, "high": 104.5, "low": 103.0, "close": 104.0, "volume": 14180}, {"date": "2025-11-27", "open": 104.5, "high": 105.0, "low": 103.0, "close": 104.5, "volume": 19000}, {"date": "2025-11-28", "open": 104.5, "high": 104.5, "low": 104.0, "close": 104.0, "volume": 16021}, {"date": "2025-12-01", "open": 103.5, "high": 104.0, "low": 103.0, "close": 104.0, "volume": 12500}, {"date": "2025-12-02", "open": 104.5, "high": 106.0, "low": 104.0, "close": 106.0, "volume": 22101}, {"date": "2025-12-03", "open": 106.5, "high": 111.0, "low": 106.5, "close": 110.5, "volume": 125900}, {"date": "2025-12-04", "open": 111.5, "high": 111.5, "low": 109.0, "close": 110.0, "volume": 89221}, {"date": "2025-12-05", "open": 109.5, "high": 109.5, "low": 108.0, "close": 108.0, "volume": 21446}, {"date": "2025-12-08", "open": 113.5, "high": 115.0, "low": 110.0, "close": 111.0, "volume": 148001}, {"date": "2025-12-09", "open": 112.0, "high": 114.5, "low": 111.0, "close": 111.5, "volume": 77400}, {"date": "2025-12-10", "open": 111.5, "high": 112.0, "low": 110.0, "close": 111.0, "volume": 32000}, {"date": "2025-12-11", "open": 111.0, "high": 112.5, "low": 110.5, "close": 111.5, "volume": 23041}, {"date": "2025-12-12", "open": 111.5, "high": 112.0, "low": 110.0, "close": 111.0, "volume": 20011}, {"date": "2025-12-15", "open": 109.5, "high": 113.5, "low": 109.5, "close": 112.0, "volume": 28220}, {"date": "2025-12-16", "open": 110.0, "high": 110.0, "low": 109.0, "close": 109.0, "volume": 13139}, {"date": "2025-12-17", "open": 109.5, "high": 115.0, "low": 109.5, "close": 113.0, "volume": 88100}, {"date": "2025-12-18", "open": 113.0, "high": 113.0, "low": 110.5, "close": 112.0, "volume": 23380}, {"date": "2025-12-19", "open": 111.0, "high": 112.5, "low": 110.5, "close": 111.0, "volume": 18738}, {"date": "2025-12-22", "open": 111.0, "high": 111.0, "low": 108.5, "close": 109.0, "volume": 84500}, {"date": "2025-12-23", "open": 108.5, "high": 109.5, "low": 108.5, "close": 109.5, "volume": 160010}, {"date": "2025-12-24", "open": 109.5, "high": 110.0, "low": 109.0, "close": 109.0, "volume": 14001}, {"date": "2025-12-26", "open": 110.0, "high": 110.5, "low": 109.0, "close": 109.0, "volume": 23100}, {"date": "2025-12-29", "open": 109.0, "high": 110.0, "low": 109.0, "close": 109.5, "volume": 13015}, {"date": "2025-12-30", "open": 108.0, "high": 109.5, "low": 107.5, "close": 107.5, "volume": 21241}, {"date": "2025-12-31", "open": 107.5, "high": 107.5, "low": 106.0, "close": 106.0, "volume": 39226}, {"date": "2026-01-02", "open": 106.0, "high": 107.5, "low": 106.0, "close": 107.0, "volume": 40010}, {"date": "2026-01-05", "open": 108.0, "high": 108.0, "low": 105.5, "close": 106.0, "volume": 22130}, {"date": "2026-01-06", "open": 106.0, "high": 106.5, "low": 105.5, "close": 106.0, "volume": 32063}, {"date": "2026-01-07", "open": 105.5, "high": 106.5, "low": 105.5, "close": 106.0, "volume": 33001}, {"date": "2026-01-08", "open": 106.0, "high": 108.5, "low": 106.0, "close": 107.0, "volume": 35064}, {"date": "2026-01-09", "open": 107.5, "high": 108.5, "low": 103.5, "close": 104.0, "volume": 191678}, {"date": "2026-01-12", "open": 105.5, "high": 105.5, "low": 104.5, "close": 105.0, "volume": 44015}, {"date": "2026-01-13", "open": 106.0, "high": 106.5, "low": 105.0, "close": 106.0, "volume": 52500}, {"date": "2026-01-14", "open": 106.0, "high": 108.0, "low": 105.5, "close": 108.0, "volume": 53050}, {"date": "2026-01-15", "open": 109.5, "high": 112.0, "low": 109.5, "close": 111.0, "volume": 139997}, {"date": "2026-01-16", "open": 111.5, "high": 111.5, "low": 108.5, "close": 109.0, "volume": 80492}, {"date": "2026-01-19", "open": 109.0, "high": 109.0, "low": 107.5, "close": 108.0, "volume": 43338}, {"date": "2026-01-20", "open": 107.5, "high": 108.5, "low": 107.5, "close": 108.0, "volume": 28721}, {"date": "2026-01-21", "open": 107.0, "high": 107.0, "low": 106.0, "close": 106.5, "volume": 50100}, {"date": "2026-01-22", "open": 107.0, "high": 107.5, "low": 106.0, "close": 107.5, "volume": 36477}, {"date": "2026-01-23", "open": 107.5, "high": 108.0, "low": 106.5, "close": 106.5, "volume": 40142}, {"date": "2026-01-26", "open": 106.5, "high": 106.5, "low": 105.5, "close": 106.0, "volume": 58026}, {"date": "2026-01-27", "open": 105.5, "high": 106.0, "low": 105.5, "close": 106.0, "volume": 33578}, {"date": "2026-01-28", "open": 105.5, "high": 106.5, "low": 105.0, "close": 106.0, "volume": 57454}, {"date": "2026-01-29", "open": 105.5, "high": 106.0, "low": 105.0, "close": 105.5, "volume": 21611}, {"date": "2026-01-30", "open": 105.0, "high": 105.0, "low": 104.5, "close": 104.5, "volume": 37032}, {"date": "2026-02-02", "open": 104.5, "high": 104.5, "low": 103.5, "close": 103.5, "volume": 49010}, {"date": "2026-02-03", "open": 105.5, "high": 105.5, "low": 104.0, "close": 105.5, "volume": 26138}, {"date": "2026-03-16", "open": 119.0, "high": 119.5, "low": 117.5, "close": 119.0, "volume": 120078}, {"date": "2026-03-17", "open": 120.5, "high": 121.5, "low": 118.5, "close": 119.5, "volume": 129032}, {"date": "2026-03-18", "open": 119.5, "high": 123.5, "low": 119.5, "close": 122.0, "volume": 221803}, {"date": "2026-03-19", "open": 121.0, "high": 121.5, "low": 119.5, "close": 120.5, "volume": 28789}, {"date": "2026-03-20", "open": 121.5, "high": 121.5, "low": 119.5, "close": 121.0, "volume": 109890}, {"date": "2026-03-23", "open": 121.0, "high": 121.0, "low": 119.5, "close": 119.5, "volume": 89532}, {"date": "2026-03-24", "open": 121.0, "high": 121.0, "low": 117.0, "close": 119.5, "volume": 156883}, {"date": "2026-03-25", "open": 115.7, "high": 116.18, "low": 115.22, "close": 115.7, "volume": 143353}, {"date": "2026-03-26", "open": 116.5, "high": 116.5, "low": 115.0, "close": 115.0, "volume": 86174}, {"date": "2026-03-27", "open": 114.5, "high": 114.5, "low": 112.5, "close": 113.0, "volume": 43587}, {"date": "2026-03-30", "open": 111.5, "high": 112.5, "low": 111.0, "close": 112.5, "volume": 49103}, {"date": "2026-03-31", "open": 112.0, "high": 113.0, "low": 110.5, "close": 111.5, "volume": 63150}, {"date": "2026-04-01", "open": 111.5, "high": 113.0, "low": 111.5, "close": 113.0, "volume": 32100}, {"date": "2026-04-02", "open": 114.0, "high": 114.5, "low": 113.5, "close": 114.0, "volume": 13696}, {"date": "2026-04-07", "open": 117.0, "high": 122.0, "low": 115.0, "close": 118.0, "volume": 234354}, {"date": "2026-04-08", "open": 120.0, "high": 120.0, "low": 118.5, "close": 119.5, "volume": 16149}, {"date": "2026-04-09", "open": 119.5, "high": 120.0, "low": 118.0, "close": 118.5, "volume": 87022}, {"date": "2026-04-10", "open": 119.5, "high": 120.0, "low": 117.5, "close": 117.5, "volume": 71367}, {"date": "2026-04-13", "open": 117.5, "high": 118.0, "low": 117.5, "close": 118.0, "volume": 8000}, {"date": "2026-04-14", "open": 117.5, "high": 118.0, "low": 115.5, "close": 118.0, "volume": 84911}, {"date": "2026-04-15", "open": 117.0, "high": 117.0, "low": 113.0, "close": 114.0, "volume": 131104}, {"date": "2026-04-16", "open": 113.5, "high": 115.0, "low": 113.0, "close": 114.0, "volume": 25777}, {"date": "2026-04-17", "open": 114.5, "high": 114.5, "low": 114.0, "close": 114.5, "volume": 25794}, {"date": "2026-04-20", "open": 115.0, "high": 115.5, "low": 112.5, "close": 112.5, "volume": 111220}, {"date": "2026-04-21", "open": 112.5, "high": 114.5, "low": 112.5, "close": 113.0, "volume": 63199}, {"date": "2026-04-22", "open": 113.0, "high": 113.5, "low": 113.0, "close": 113.5, "volume": 59578}]}