{"generated_at": "2026-04-23 14:31:18", "count": 52, "items": [{"sid": "4577", "name": "達航科技", "close": 175.0, "turnover_rate": 71.2, "strength": "跌過轉強", "source": "每日即時、MACD縮頭"}, {"sid": "8021", "name": "尖點", "close": 471.5, "turnover_rate": 54.9, "strength": "跌過轉強", "source": "每日即時"}, {"sid": "3228", "name": "金麗科", "close": 201.5, "turnover_rate": 692.0, "strength": "跌過轉強", "source": "每日即時、週RSI衝浪"}, {"sid": "8240", "name": "華宏", "close": 72.8, "turnover_rate": 530.4, "strength": "一路強", "source": "每日即時、BBI戰法、MACD縮頭"}, {"sid": "1721", "name": "三晃", "close": 29.95, "turnover_rate": 736.3, "strength": "跌過轉強", "source": "每日即時"}, {"sid": "3443", "name": "創意", "close": 3910.0, "turnover_rate": 97.5, "strength": "一路強", "source": "每日即時"}, {"sid": "7711", "name": "永擎", "close": 372.0, "turnover_rate": 553.5, "strength": "一路強", "source": "每日即時、BBI戰法"}, {"sid": "8162", "name": "微矽電子-創", "close": 52.6, "turnover_rate": 646.0, "strength": "一路強", "source": "每日即時"}, {"sid": "3162", "name": "精確", "close": 83.9, "turnover_rate": 610.5, "strength": "一路強", "source": "每日即時"}, {"sid": "4739", "name": "康普", "close": 100.5, "turnover_rate": 456.7, "strength": "跌過轉強", "source": "每日即時、BBI戰法、MACD縮頭"}, {"sid": "2501", "name": "國建", "close": 26.25, "turnover_rate": 286.1, "strength": "跌過轉強", "source": "每日即時"}, {"sid": "2474", "name": "可成", "close": 231.5, "turnover_rate": 518.5, "strength": "一路強", "source": "每日即時"}, {"sid": "9136", "name": "巨騰-DR", "close": 12.15, "turnover_rate": 329.7, "strength": "一路強", "source": "決策池、週RSI衝浪"}, {"sid": "6136", "name": "富爾特", "close": 28.0, "turnover_rate": 759.6, "strength": "跌過轉強", "source": "週線衝浪、MACD縮頭"}, {"sid": "6877", "name": "鏵友益", "close": 185.5, "turnover_rate": 477.0, "strength": "跌過轉強", "source": "週線衝浪、BBI戰法、MACD縮頭"}, {"sid": "6944", "name": "兆聯實業", "close": 970.0, "turnover_rate": 167.0, "strength": "跌過轉強", "source": "週RSI衝浪、BBI戰法、MACD縮頭"}, {"sid": "6658", "name": "聯策", "close": 100.5, "turnover_rate": 509.3, "strength": "跌過轉強", "source": "週RSI衝浪、MACD縮頭"}, {"sid": "6782", "name": "視陽", "close": 231.0, "turnover_rate": 185.8, "strength": "跌過轉強", "source": "週RSI衝浪、MACD縮頭"}, {"sid": "1304", "name": "台聚", "close": 14.65, "turnover_rate": 122.9, "strength": "跌過轉強", "source": "歷史資金衝浪、BBI戰法、MACD縮頭"}, {"sid": "1309", "name": "台達化", "close": 20.45, "turnover_rate": 125.2, "strength": "跌過轉強", "source": "歷史資金衝浪、MACD縮頭"}, {"sid": "1323", "name": "永裕", "close": 22.25, "turnover_rate": 251.0, "strength": "跌過轉強", "source": "歷史資金衝浪、MACD縮頭"}, {"sid": "1102", "name": "亞泥", "close": 36.05, "turnover_rate": 200.0, "strength": "一路強", "source": "BBI戰法"}, {"sid": "2855", "name": "統一證", "close": 34.0, "turnover_rate": 227.0, "strength": "跌過轉強", "source": "BBI戰法、MACD縮頭"}, {"sid": "1708", "name": "東鹼", "close": 39.4, "turnover_rate": 77.1, "strength": "跌過轉強", "source": "BBI戰法、MACD縮頭"}, {"sid": "6907", "name": "雅特力-KY", "close": 140.0, "turnover_rate": 565.9, "strength": "跌過轉強", "source": "BBI戰法、MACD縮頭"}, {"sid": "3675", "name": "德微", "close": 238.0, "turnover_rate": 609.2, "strength": "跌過轉強", "source": "BBI戰法、MACD縮頭"}, {"sid": "6415", "name": "矽力*-KY", "close": 415.5, "turnover_rate": 400.7, "strength": "跌過轉強", "source": "BBI戰法、MACD縮頭"}, {"sid": "6761", "name": "穩得", "close": 217.5, "turnover_rate": 337.6, "strength": "一路強", "source": "BBI戰法、MACD縮頭"}, {"sid": "7805", "name": "威聯通", "close": 722.0, "turnover_rate": 213.5, "strength": "跌過轉強", "source": "BBI戰法"}, {"sid": "1714", "name": "和桐", "close": 9.95, "turnover_rate": 190.3, "strength": "跌過轉強", "source": "MACD縮頭"}, {"sid": "2243", "name": "宏旭-KY", "close": 24.0, "turnover_rate": 128.9, "strength": "跌過轉強", "source": "MACD縮頭"}, {"sid": "3205", "name": "佰研", "close": 60.4, "turnover_rate": 102.4, "strength": "跌過轉強", "source": "MACD縮頭"}, {"sid": "5243", "name": "乙盛-KY", "close": 123.5, "turnover_rate": 101.4, "strength": "跌過轉強", "source": "MACD縮頭"}, {"sid": "9949", "name": "琉園", "close": 36.7, "turnover_rate": 223.3, "strength": "跌過轉強", "source": "MACD縮頭"}, {"sid": "2108", "name": "南帝", "close": 27.1, "turnover_rate": 313.5, "strength": "一路強", "source": "MACD縮頭"}, {"sid": "7751", "name": "竑騰", "close": 2195.0, "turnover_rate": 281.1, "strength": "跌過轉強", "source": "MACD縮頭"}, {"sid": "2221", "name": "大甲", "close": 41.65, "turnover_rate": 832.7, "strength": "一路強", "source": "MACD縮頭"}, {"sid": "7734", "name": "印能科技", "close": 3465.0, "turnover_rate": 261.7, "strength": "跌過轉強", "source": "MACD縮頭"}, {"sid": "8109", "name": "博大", "close": 120.0, "turnover_rate": 475.8, "strength": "一路強", "source": "MACD縮頭"}, {"sid": "5519", "name": "隆大", "close": 33.05, "turnover_rate": 210.8, "strength": "跌過轉強", "source": "MACD縮頭"}, {"sid": "1305", "name": "華夏", "close": 15.05, "turnover_rate": 127.4, "strength": "跌過轉強", "source": "MACD縮頭"}, {"sid": "3338", "name": "泰碩", "close": 85.4, "turnover_rate": 626.5, "strength": "一路強", "source": "MACD縮頭"}, {"sid": "6015", "name": "宏遠證", "close": 13.35, "turnover_rate": 206.0, "strength": "跌過轉強", "source": "MACD縮頭"}, {"sid": "6861", "name": "睿生光電", "close": 235.5, "turnover_rate": 295.3, "strength": "一路強", "source": "MACD縮頭"}, {"sid": "1308", "name": "亞聚", "close": 15.65, "turnover_rate": 90.8, "strength": "跌過轉強", "source": "MACD縮頭"}, {"sid": "5864", "name": "致和證", "close": 25.55, "turnover_rate": 219.9, "strength": "跌過轉強", "source": "MACD縮頭"}, {"sid": "6789", "name": "采鈺", "close": 515.0, "turnover_rate": 426.6, "strength": "一路強", "source": "MACD縮頭"}, {"sid": "3709", "name": "鑫聯大投控", "close": 79.9, "turnover_rate": 249.9, "strength": "跌過轉強", "source": "MACD縮頭"}, {"sid": "6290", "name": "良維", "close": 306.5, "turnover_rate": 278.1, "strength": "跌過轉強", "source": "MACD縮頭"}, {"sid": "1595", "name": "川寶", "close": 60.6, "turnover_rate": 525.5, "strength": "一路強", "source": "MACD縮頭"}, {"sid": "6234", "name": "高僑", "close": 42.05, "turnover_rate": 492.6, "strength": "一路強", "source": "MACD縮頭"}, {"sid": "7744", "name": "崴寶", "close": 548.0, "turnover_rate": 308.9, "strength": "一路強", "source": "MACD縮頭"}]}